disent/__init__.py
disent/dataset/__init__.py
disent/dataset/_base.py
disent/dataset/data/__init__.py
disent/dataset/data/_episodes.py
disent/dataset/data/_episodes__custom.py
disent/dataset/data/_groundtruth.py
disent/dataset/data/_groundtruth__cars3d.py
disent/dataset/data/_groundtruth__dsprites.py
disent/dataset/data/_groundtruth__dsprites_imagenet.py
disent/dataset/data/_groundtruth__mpi3d.py
disent/dataset/data/_groundtruth__norb.py
disent/dataset/data/_groundtruth__shapes3d.py
disent/dataset/data/_groundtruth__sprites.py
disent/dataset/data/_groundtruth__xcolumns.py
disent/dataset/data/_groundtruth__xyobject.py
disent/dataset/data/_groundtruth__xysquares.py
disent/dataset/data/_random__teapots3d.py
disent/dataset/data/_raw.py
disent/dataset/sampling/__init__.py
disent/dataset/sampling/_base.py
disent/dataset/sampling/_groundtruth__dist.py
disent/dataset/sampling/_groundtruth__pair.py
disent/dataset/sampling/_groundtruth__pair_orig.py
disent/dataset/sampling/_groundtruth__single.py
disent/dataset/sampling/_groundtruth__triplet.py
disent/dataset/sampling/_groundtruth__walk.py
disent/dataset/sampling/_random__any.py
disent/dataset/sampling/_random__episodes.py
disent/dataset/sampling/_single.py
disent/dataset/transform/__init__.py
disent/dataset/transform/_augment.py
disent/dataset/transform/_augment_disent.py
disent/dataset/transform/_transforms.py
disent/dataset/transform/functional.py
disent/dataset/util/__init__.py
disent/dataset/util/datafile.py
disent/dataset/util/state_space.py
disent/dataset/util/stats.py
disent/dataset/util/formats/__init__.py
disent/dataset/util/formats/hdf5.py
disent/dataset/util/formats/npz.py
disent/dataset/wrapper/__init__.py
disent/dataset/wrapper/_base.py
disent/dataset/wrapper/_dither.py
disent/dataset/wrapper/_masked.py
disent/frameworks/__init__.py
disent/frameworks/_ae_mixin.py
disent/frameworks/_framework.py
disent/frameworks/ae/__init__.py
disent/frameworks/ae/_supervised__adaneg_tae.py
disent-0.8.0.dist-info/LICENSE.txt
disent-0.8.0.dist-info/METADATA
disent-0.8.0.dist-info/WHEEL
disent-0.8.0.dist-info/top_level.txt
disent-0.8.0.dist-info/RECORD
