Metadata-Version: 2.1
Name: disent
Version: 0.8.0
Summary: Vae disentanglement framework built with pytorch lightning.
Home-page: https://github.com/nmichlo/disent
Author: Nathan Juraj Michlo
Author-email: NathanJMichlo@gmail.com
Classifier: License :: OSI Approved :: MIT License
Classifier: Operating System :: OS Independent
Classifier: Programming Language :: Python :: 3.8
Classifier: Programming Language :: Python :: 3.9
Classifier: Programming Language :: Python :: 3.10
Classifier: Intended Audience :: Science/Research
Requires-Python: >=3.8
License-File: LICENSE.txt
Requires-Dist: pip (>=21.0)
Requires-Dist: numpy (>=1.19.0)
Requires-Dist: torch (>=2.0.0)
Requires-Dist: torchvision (>=0.15.0)
Requires-Dist: lightning (>=2.0.0)
Requires-Dist: scipy (>=1.7.0)
Requires-Dist: scikit-learn (>=1.0.0)
Requires-Dist: Pillow (>=8.2.0)
Requires-Dist: h5py (>=2.10.0)
Requires-Dist: requests
Requires-Dist: tqdm (>=4.60.0)
